geney/Oncosplice.py
geney/__init__.py
geney/engines.py
geney/pipelines.py
geney/samples.py
geney/splice_graph.py
geney/splice_graph_archive.py
geney/splicing_table.py
geney/transcripts.py
geney/utils.py
geney/variants.py
geney/models/openspliceai-mane/10000nt/model_10000nt_rs10.pt
geney/models/openspliceai-mane/10000nt/model_10000nt_rs11.pt
geney/models/openspliceai-mane/10000nt/model_10000nt_rs12.pt
geney/models/openspliceai-mane/10000nt/model_10000nt_rs13.pt
geney/models/openspliceai-mane/10000nt/model_10000nt_rs14.pt
geney-1.4.45.dist-info/METADATA
geney-1.4.45.dist-info/WHEEL
geney-1.4.45.dist-info/top_level.txt
geney-1.4.45.dist-info/RECORD
