Metadata-Version: 2.4
Name: geney
Version: 1.4.45
Summary: A Python package for gene expression modeling.
Home-page: https://github.com/nicolaslynn/geney
Author: Nicolas Lynn
Author-email: nicolasalynn@gmail.com
License: Free for non-commercial use
Classifier: Development Status :: 1 - Planning
Classifier: Intended Audience :: Science/Research
Classifier: License :: Free for non-commercial use
Classifier: Operating System :: POSIX :: Linux
Classifier: Operating System :: MacOS
Classifier: Programming Language :: Python :: 3.9
Requires-Python: >3.10
Requires-Dist: numpy<2.0
Requires-Dist: pandas==2.1.4
Requires-Dist: biopython>=1.81
Requires-Dist: matplotlib
Requires-Dist: seaborn
Requires-Dist: torch
Requires-Dist: openspliceai
Requires-Dist: seqmat
Dynamic: author
Dynamic: author-email
Dynamic: classifier
Dynamic: home-page
Dynamic: license
Dynamic: requires-dist
Dynamic: requires-python
Dynamic: summary
